poisson_approval/__init__.py
poisson_approval/best_response/BestResponse.py
poisson_approval/best_response/BestResponseAntiPlurality.py
poisson_approval/best_response/BestResponseApproval.py
poisson_approval/best_response/BestResponsePlurality.py
poisson_approval/best_response/__init__.py
poisson_approval/constants/EquilibriumStatus.py
poisson_approval/constants/Focus.py
poisson_approval/constants/__init__.py
poisson_approval/constants/basic_constants.py
poisson_approval/containers/AnalyzedStrategies.py
poisson_approval/containers/Scores.py
poisson_approval/containers/Winners.py
poisson_approval/containers/__init__.py
poisson_approval/events/Asymptotic.py
poisson_approval/events/Event.py
poisson_approval/events/EventDuo.py
poisson_approval/events/EventPivotStrict.py
poisson_approval/events/EventPivotTij.py
poisson_approval/events/EventPivotTjk.py
poisson_approval/events/EventPivotWeak.py
poisson_approval/events/EventTrio.py
poisson_approval/events/EventTrio1t.py
poisson_approval/events/EventTrio2t.py
poisson_approval/events/__init__.py
poisson_approval/iterables/IterableProfileDiscreteGrid.py
poisson_approval/iterables/IterableProfileHistogramGrid.py
poisson_approval/iterables/IterableProfileNoisyDiscreteGrid.py
poisson_approval/iterables/IterableProfileOrdinalGrid.py
poisson_approval/iterables/IterableProfileTwelveGrid.py
poisson_approval/iterables/IterableSimplexGrid.py
poisson_approval/iterables/IterableStrategyOrdinal.py
poisson_approval/iterables/IterableStrategyThresholdGrid.py
poisson_approval/iterables/IterableStrategyTwelve.py
poisson_approval/iterables/IterableTauVectorGrid.py
poisson_approval/iterables/__init__.py
poisson_approval/meta_analysis/NiceStatsProfileOrdinal.py
poisson_approval/meta_analysis/__init__.py
poisson_approval/meta_analysis/binary_condorcet.py
poisson_approval/meta_analysis/binary_plots.py
poisson_approval/meta_analysis/binary_shortcuts.py
poisson_approval/meta_analysis/colors.py
poisson_approval/meta_analysis/convergence_test.py
poisson_approval-0.31.0.dist-info/AUTHORS.rst
poisson_approval-0.31.0.dist-info/LICENSE
poisson_approval-0.31.0.dist-info/METADATA
poisson_approval-0.31.0.dist-info/WHEEL
poisson_approval-0.31.0.dist-info/top_level.txt
poisson_approval-0.31.0.dist-info/RECORD
