Metadata-Version: 2.1
Name: poisson-approval
Version: 0.31.0
Summary: Poisson Approval studies the Poisson Game of Approval Voting.
Home-page: https://github.com/francois-durand/poisson_approval
Author: François Durand
Author-email: fradurand@gmail.com
License: GNU General Public License v3
Keywords: poisson_approval
Platform: UNKNOWN
Classifier: Development Status :: 2 - Pre-Alpha
Classifier: Intended Audience :: Developers
Classifier: License :: OSI Approved :: GNU General Public License v3 (GPLv3)
Classifier: Natural Language :: English
Classifier: Programming Language :: Python :: 3
Classifier: Programming Language :: Python :: 3.6
Classifier: Programming Language :: Python :: 3.7
Classifier: Programming Language :: Python :: 3.8
Requires-Python: >=3.6
License-File: LICENSE
License-File: AUTHORS.rst
Requires-Dist: numpy
Requires-Dist: scipy
Requires-Dist: matplotlib
Requires-Dist: python-ternary
Requires-Dist: shapely
Requires-Dist: sympy
